core/__init__.py
core/cleaner.py
core/optimizer.py
core/scanner.py
mac_clean_cli-1.0.0.dist-info/licenses/LICENSE
models/__init__.py
models/scan_result.py
ui/__init__.py
ui/components.py
ui/interface.py
utils/__init__.py
utils/backup.py
utils/config.py
utils/logger.py
mac_clean_cli-1.0.0.dist-info/METADATA
mac_clean_cli-1.0.0.dist-info/WHEEL
mac_clean_cli-1.0.0.dist-info/entry_points.txt
mac_clean_cli-1.0.0.dist-info/top_level.txt
mac_clean_cli-1.0.0.dist-info/RECORD
