Metadata-Version: 2.4
Name: mac-clean-cli
Version: 1.0.0
Summary: A beautiful console application for cleaning and optimizing macOS
Home-page: https://github.com/qdenka/MacCleanCLI
Author: QDenka
Author-email: QDenka <denis@kaban.dev>
Project-URL: Homepage, https://github.com/yourusername/macos-cleaner
Project-URL: Documentation, https://github.com/yourusername/macos-cleaner/wiki
Project-URL: Repository, https://github.com/yourusername/macos-cleaner.git
Project-URL: Issues, https://github.com/yourusername/macos-cleaner/issues
Keywords: macos,cleaner,optimization,system,utility
Classifier: Development Status :: 4 - Beta
Classifier: Environment :: Console
Classifier: Intended Audience :: End Users/Desktop
Classifier: Operating System :: MacOS :: MacOS X
Classifier: Programming Language :: Python :: 3
Classifier: Programming Language :: Python :: 3.10
Classifier: Programming Language :: Python :: 3.11
Classifier: Programming Language :: Python :: 3.12
Classifier: Topic :: System :: Systems Administration
Classifier: Topic :: Utilities
Requires-Python: >=3.10
License-File: LICENSE
Requires-Dist: rich>=13.7.0
Requires-Dist: psutil>=5.9.0
Requires-Dist: click>=8.1.0
Provides-Extra: dev
Requires-Dist: pytest>=7.4.0; extra == "dev"
Requires-Dist: pytest-cov>=4.1.0; extra == "dev"
Requires-Dist: black>=23.0.0; extra == "dev"
Requires-Dist: flake8>=6.1.0; extra == "dev"
Requires-Dist: mypy>=1.5.0; extra == "dev"
Requires-Dist: homebrew-pypi-poet>=0.10.0; extra == "dev"
Dynamic: author
Dynamic: home-page
Dynamic: license-file
Dynamic: requires-python
